[
  { "argument": "neth kit", "description": "Shulkers with full netherite sets" },
  { "argument": "stack", "description": "Stacks of an item" },
  { "argument": "gapple", "description": "Golden apple" },
  { "argument": "gap", "description": "Golden apple" },
  { "argument": "trims", "description": "Armor trims" },
  { "argument": "tools", "description": "Shovel, Axe, Sword, Hoe, Pickaxe, and Shears" },
  { "argument": "fuel", "description": "Fuel sources for Blast Furnace, Smoker, and Furnace" },
  { "argument": "block", "description": "Blocks items" },
  { "argument": "pvp gear", "description": "Bottle o’ Enchanting, Respawn anchors, Totem of Undying, End Crystal, Crossbow, Bow, Arrows, Sword, Axe" },
  { "argument": "custom", "description": "Amethyst Shovel, Amethyst Sell Axe (Wand), Amethyst Axe, Amethyst Pickaxe (Drill), Amethyst Bucket, Shard Booster" },
  { "argument": "dia kit", "description": "Shulkers with full diamond set" },
  { "argument": "regear", "description": "Shulkers containing Totems Of Undying" },
  { "argument": "ores", "description": "Coal, Copper, Diamond, Redstone, Quartz, Emerald, Gold, Iron, Lapis (raw and ore form)" },
  { "argument": "flower", "description": "Flowers" },
  { "argument": "nether", "description": "Nether related items" },
  { "argument": "end", "description": "End related items" },
  { "argument": "neth", "description": "Nether related items with netherite items" },
  { "argument": "seed", "description": "Seeds and crops items" },
  { "argument": "brewing", "description": "Potions, Water Bucket, Brewing Stand, Blaze Powder" },
  { "argument": "ingredients", "description": "Potion ingredients" },
  { "argument": "farming", "description": "Water, Lava, Dirt, Coral block, Composter, Bonemeal, Axe, Mud, Hoe" },
  { "argument": "enchant", "description": "Enchanted Books and Bottle o’ Enchanting" },
  { "argument": "plants", "description": "Plant items" },
  { "argument": "meat", "description": "Raw and cooked meat" },
  { "argument": "light", "description": "Light sources items" },
  { "argument": "weapon", "description": "Sword, Axe, Bow, Crossbow" },
  { "argument": "mob drops", "description": "drops from mobs" },
  { "argument": "fish", "description": "Fish and Fishing Pole" },
  { "argument": "enchanted", "description": "Enchanted items" },
  { "argument": "stand", "description": "Armor Stand and Brewing Stand" },
  { "argument": "potion", "description": "Potions" },
  { "argument": "dur 3", "description": "Firework Rocket durability 3" },
  { "argument": "dur 2", "description": "Firework Rocket durability 2" },
  { "argument": "dur 1", "description": "Firework Rocket durability 1" },
  { "argument": "gear", "description": "Leggings, Chestplate, Helmet, Boots" },
  { "argument": "food", "description": "Food items" },
  { "argument": "wand", "description": "Amethyst Sell Axe" },
  { "argument": "drill", "description": "Amethyst Pickaxe" },
  { "argument": "armor", "description": "Armor, trims and Armor Stand" },
  { "argument": "pvp", "description": "Armor, Bottle o’ Enchanting, Respawn Anchor, Arrows, Crossbow" },
  { "argument": "<color>", "description": "Items matching <color> argument" },
  { "argument": "shulk", "description": "Empty Shulker or shulker containing items" },
  { "argument": "wood", "description": "wood related items" }

]